py_wave_runup/__init__.py
py_wave_runup/datasets.py
py_wave_runup/ensembles.py
py_wave_runup/models.py
py_wave_runup/utils.py
py_wave_runup/datasets/power18.csv
py_wave_runup/datasets/beuzen18/generate_beuzen18_model.py
py_wave_runup/datasets/beuzen18/gp_runup_model.joblib
py_wave_runup/datasets/beuzen18/lidar_runup_data_for_GP_training.csv
py_wave_runup-0.1.12.dist-info/METADATA
py_wave_runup-0.1.12.dist-info/WHEEL
py_wave_runup-0.1.12.dist-info/RECORD
