Metadata-Version: 2.4
Name: py-wave-runup
Version: 0.1.12
Summary: Empirical wave runup models implemented in Python
Project-URL: Homepage, https://github.com/chrisleaman/py-wave-runup
Project-URL: Repository, https://github.com/chrisleaman/py-wave-runup
Project-URL: Documentation, https://py-wave-runup.readthedocs.io
Author: Chris Leaman
License: GPL-3.0+
Classifier: Development Status :: 4 - Beta
Classifier: Intended Audience :: Science/Research
Classifier: License :: OSI Approved :: GNU General Public License v3 or later (GPLv3+)
Classifier: Programming Language :: Python :: 3
Classifier: Programming Language :: Python :: 3.10
Classifier: Programming Language :: Python :: 3.11
Classifier: Programming Language :: Python :: 3.12
Classifier: Programming Language :: Python :: 3.13
Classifier: Programming Language :: Python :: 3.14
Classifier: Topic :: Scientific/Engineering
Requires-Python: <3.15,>=3.10
Requires-Dist: joblib>=1.3
Requires-Dist: numpy>=1.24
Requires-Dist: pandas>=2.0
Requires-Dist: scikit-learn>=1.3
